policykit/__init__.py
policykit/cli.py
policykit/conftest.py
policykit/errors.py
policykit/models.py
policykit/test_conftest.py
policykit/test_models.py
policykit-0.4.0.dist-info/entry_points.txt
policykit-0.4.0.dist-info/LICENSE
policykit-0.4.0.dist-info/WHEEL
policykit-0.4.0.dist-info/METADATA
policykit-0.4.0.dist-info/RECORD
