Metadata-Version: 2.1
Name: policykit
Version: 0.4.0
Summary: A set of utilities and classes for working with Open Policy Agent based tools, including Gatekeeper and Conftest
Home-page: https://github.com/garethr/policykit
License: Apache-2.0
Author: Gareth Rushgrove
Author-email: gareth@morethanseven.net
Requires-Python: >=3.7,<4.0
Classifier: License :: OSI Approved :: Apache Software License
Classifier: Programming Language :: Python :: 3
Classifier: Programming Language :: Python :: 3.7
Classifier: Programming Language :: Python :: 3.8
Requires-Dist: PyYAML (>=5.1,<6.0)
Requires-Dist: attrs (>=19.3,<20.0)
Requires-Dist: click (>=7.0,<8.0)
Requires-Dist: colorama (>=0.4.1,<0.5.0)
Requires-Dist: dataclasses-json (>=0.3.5,<0.4.0)
Requires-Dist: delegator.py (>=0.1.1,<0.2.0)
Project-URL: Repository, https://github.com/garethr/policykit
